llm_task_handler/__init__.py
llm_task_handler/chatroom.py
llm_task_handler/dispatch.py
llm_task_handler/handler.py
llm_task_handler/select.py
llm_task_handler-2.0.1.dist-info/LICENSE
llm_task_handler-2.0.1.dist-info/METADATA
llm_task_handler-2.0.1.dist-info/WHEEL
llm_task_handler-2.0.1.dist-info/top_level.txt
llm_task_handler-2.0.1.dist-info/RECORD
