Metadata-Version: 2.1
Name: llm-task-handler
Version: 2.0.1
Summary: LLM Task Handler
Home-page: 
Author: Jimming Cheng
Author-email: jimming@gmail.com
Classifier: Programming Language :: Python :: 3
Classifier: License :: OSI Approved :: MIT License
Classifier: Operating System :: OS Independent
License-File: LICENSE
Requires-Dist: langchain
